streamlit_gpt_vis/__init__.py
streamlit_gpt_vis/frontend/dist/bootstrap.min.css
streamlit_gpt_vis/frontend/dist/index.html
streamlit_gpt_vis/frontend/dist/assets/index-DVvu74bu.js
streamlit_gpt_vis/frontend/dist/assets/index-Da9KaUzh.js
streamlit_gpt_vis/frontend/dist/assets/worker-dpUGKuRO.js
streamlit_gpt_vis-0.0.3.dist-info/LICENSE
streamlit_gpt_vis-0.0.3.dist-info/METADATA
streamlit_gpt_vis-0.0.3.dist-info/WHEEL
streamlit_gpt_vis-0.0.3.dist-info/top_level.txt
streamlit_gpt_vis-0.0.3.dist-info/RECORD
