Metadata-Version: 2.1
Name: streamlit-gpt-vis
Version: 0.0.3
Summary: Binding for GPT-Vis, Components for GPTs, generative AI, and LLM projects. Not only UI Components.
Home-page: https://github.com/antvis/GPT-Vis/bindings/streamlit-gpt-vis
Author: @lvisei
Author-email: yunji.me@outlook.com
License: MIT
Platform: UNKNOWN
Requires-Python: >=3.7
License-File: LICENSE
Requires-Dist: streamlit (>=0.63)
